uchain/__init__.py
uchain/uchain.py
uchain-0.1.0.dist-info/AUTHORS.rst
uchain-0.1.0.dist-info/LICENSE
uchain-0.1.0.dist-info/METADATA
uchain-0.1.0.dist-info/WHEEL
uchain-0.1.0.dist-info/top_level.txt
uchain-0.1.0.dist-info/RECORD
