Metadata-Version: 2.1
Name: uchain
Version: 0.1.0
Summary: A tiny implementation of a blockchain, for educational purposes.
Home-page: https://github.com/reale/uchain
Author: Roberto Reale
Author-email: roberto@reale.me
License: MIT license
Keywords: uchain
Platform: UNKNOWN
Classifier: Development Status :: 2 - Pre-Alpha
Classifier: Intended Audience :: Developers
Classifier: License :: OSI Approved :: MIT License
Classifier: Natural Language :: English
Classifier: Programming Language :: Python :: 3
Classifier: Programming Language :: Python :: 3.5
Classifier: Programming Language :: Python :: 3.6
Classifier: Programming Language :: Python :: 3.7
Classifier: Programming Language :: Python :: 3.8
Requires-Python: >=3.5
